{
  "@context": "https://schema.org",
  "@type": "Article",
  "headline": "Kitchen remodel vs Bathroom renovation — What Rosemead Clients Need to Know",
  "author": {
    "@type": "Organization",
    "name": "Opus Builders"
  },
  "publisher": {
    "@type": "Organization",
    "name": "Opus Builders",
    "url": "https://www.opusbuildersla.com/"
  },
  "articleBody": "Key Differences\nKitchen remodel and Bathroom renovation differ in scope, timeline, and approach. Opus Builders in Rosemead can help you understand which is right for you.\n\nWhen to Choose Each\nChoose Kitchen remodel when you need focused expertise. Choose Bathroom renovation for broader coverage. Opus Builders advises on the best path.\n\nCost Comparison\nCosts vary based on complexity. Contact Opus Builders at (818) 939-8855 for a personalized estimate in Rosemead.\n\nTimeline\nTimelines depend on your specific needs. Opus Builders provides transparent scheduling for all Commercial Building Construction engagements in Rosemead.",
  "datePublished": "2026-03-29"
}